quantinuum_sphinx/__init__.py
quantinuum_sphinx/page.html
quantinuum_sphinx/static/assets/github.svg
quantinuum_sphinx/static/assets/quantinuum_favicon.svg
quantinuum_sphinx/static/assets/slack.svg
quantinuum_sphinx/static/assets/stack.svg
quantinuum_sphinx/static/assets/test.svg
quantinuum_sphinx/static/injectNav.global.js
quantinuum_sphinx/static/styles/quantinuum-sphinx.css
quantinuum_sphinx/static/styles/quantinuum-ui-tailwind.css
quantinuum_sphinx/static/styles/quantinuum-ui-tokens.css
quantinuum_sphinx/static/syncTheme.global.js
quantinuum_sphinx/theme.toml
quantinuum_sphinx-0.6.0.dist-info/entry_points.txt
quantinuum_sphinx-0.6.0.dist-info/LICENSE
quantinuum_sphinx-0.6.0.dist-info/METADATA
quantinuum_sphinx-0.6.0.dist-info/WHEEL
quantinuum_sphinx-0.6.0.dist-info/RECORD
