Metadata-Version: 2.3
Name: quantinuum_sphinx
Version: 0.6.0
Summary: 
Author: Aidan Keay
Author-email: aidan.keay@quantinuum.com
Requires-Python: >=3.10,<4.0
Classifier: Programming Language :: Python :: 3
Classifier: Programming Language :: Python :: 3.10
Classifier: Programming Language :: Python :: 3.11
Classifier: Programming Language :: Python :: 3.12
Classifier: Programming Language :: Python :: 3.13
Requires-Dist: furo (>=2024.5.6,<2025.0.0)
